README.md
setup.py
test/test.py
tkitMatch/Match.py
tkitMatch/__init__.py
tkitMatch.egg-info/PKG-INFO
tkitMatch.egg-info/SOURCES.txt
tkitMatch.egg-info/dependency_links.txt
tkitMatch.egg-info/top_level.txt